spark_board/__init__.py
spark_board/default_settings.py
spark_board/env.py
spark_board/html.py
spark_board/plan_extractor/__init__.py
spark_board/plan_extractor/dag.py
spark_board/plan_extractor/dag_builder.py
spark_board/plan_extractor/errors.py
spark_board/plan_extractor/py4j_utils.py
spark_board/plan_extractor/transformations_dag.py
spark_board/plan_extractor/dag_simplification/__init__.py
spark_board/plan_extractor/dag_simplification/dag_simplifier.py
spark_board/plan_extractor/dag_simplification/merge_datasource_and_alias.py
spark_board/plan_extractor/dag_simplification/merge_join_and_project.py
spark_board/plan_extractor/transformation_node_builders/__init__.py
spark_board/plan_extractor/transformation_node_builders/aggregate_node_builder.py
spark_board/plan_extractor/transformation_node_builders/alias_node_builder.py
spark_board/plan_extractor/transformation_node_builders/deduplicate_node_builder.py
spark_board/plan_extractor/transformation_node_builders/except_node_builder.py
spark_board/plan_extractor/transformation_node_builders/expand_node_builder.py
spark_board/plan_extractor/transformation_node_builders/filter_node_builder.py
spark_board/plan_extractor/transformation_node_builders/generate_node_builder.py
spark_board/plan_extractor/transformation_node_builders/intersect_node_builder.py
spark_board/plan_extractor/transformation_node_builders/join_node_builder.py
spark_board/plan_extractor/transformation_node_builders/limit_node_builder.py
spark_board/plan_extractor/transformation_node_builders/logical_rdd_node_builder.py
spark_board/plan_extractor/transformation_node_builders/logical_relation_node_builder.py
spark_board/plan_extractor/transformation_node_builders/project_node_builder.py
spark_board/plan_extractor/transformation_node_builders/repartition_node_builder.py
spark_board/plan_extractor/transformation_node_builders/repository.py
spark_board/plan_extractor/transformation_node_builders/sample_node_builder.py
spark_board-1.0.0.dist-info/LICENSE
spark_board-1.0.0.dist-info/METADATA
spark_board-1.0.0.dist-info/WHEEL
spark_board-1.0.0.dist-info/top_level.txt
spark_board-1.0.0.dist-info/RECORD
