Metadata-Version: 2.1
Name: spark-board
Version: 1.0.0
Summary: Interactive visualization of Spark jobs
Home-page: https://github.com/alijdens/spark-board
Author: Axel Lijdens, Ezequiel Werner
Classifier: Programming Language :: Python :: 3
Classifier: License :: OSI Approved :: MIT License
Classifier: Operating System :: OS Independent
Requires-Python: >3.6
License-File: LICENSE
Requires-Dist: pyspark >3
